<?xml version="1.0" encoding="utf-8" ?>
<dwsync>
<file name="arrow-left-white.png" server="itszas.edu.mx" local="130586700000000000" remote="130586700000000000" Dst="1" />
<file name="arrow-right-white.png" server="itszas.edu.mx" local="130586700000000000" remote="130586700000000000" Dst="1" />
<file name="border8.png" server="itszas.edu.mx" local="130586699400000000" remote="130586699400000000" Dst="1" />
<file name="chevron-left.png" server="itszas.edu.mx" local="130573630200000000" remote="130573630200000000" Dst="1" />
<file name="lorempixel1.jpg" server="itszas.edu.mx" local="130573630200000000" remote="130573630200000000" Dst="1" />
<file name="lorempixel2.jpg" server="itszas.edu.mx" local="130573630200000000" remote="130573630200000000" Dst="1" />
<file name="retina_wood.png" server="itszas.edu.mx" local="130586700000000000" remote="130586700000000000" Dst="1" />
<file name="speech-bubble-left.png" server="itszas.edu.mx" local="130586700000000000" remote="130586700000000000" Dst="1" />
<file name="speech-bubble-right.png" server="itszas.edu.mx" local="130586690400000000" remote="130586690400000000" Dst="1" />
</dwsync>